orite/__init__.py
orite/_orite_exclude.txt
orite/command_line.py
orite/orite.py
orite/orite_exclude.txt
orite-0.0.18.dist-info/METADATA
orite-0.0.18.dist-info/RECORD
orite-0.0.18.dist-info/WHEEL
orite-0.0.18.dist-info/entry_points.txt
orite-0.0.18.dist-info/top_level.txt
