Metadata-Version: 2.1
Name: orite
Version: 0.0.18
Summary: orite - an opinionated Python rsync wrapper
Home-page: https://github.com/meyouwe/orite
Author: Maarten Idema
Author-email: maarten@mountdeluxe.com
License: UNKNOWN
Platform: UNKNOWN
Classifier: Programming Language :: Python :: 3
Classifier: License :: OSI Approved :: MIT License
Classifier: Operating System :: OS Independent
Classifier: Topic :: Internet
